{"cameraMode":{"drawMode":0,"name":"Shaded","section":"Shading Mode"},"sceneLighting":false,"audioPlay":false,"sceneViewState":{"m_AlwaysRefresh":false,"showFog":true,"showSkybox":false,"showFlares":true,"showImageEffects":true,"showParticleSystems":true,"showVisualEffectGraphs":true,"m_FxEnabled":true},"in2DMode":false,"pivot":{"x":-36.192108154296878,"y":46.62895202636719,"z":6.7244873046875},"rotation":{"x":0.0010776726994663478,"y":-0.9954859018325806,"z":-0.09404490888118744,"w":-0.011341864243149758},"size":606.34033203125,"orthographic":false}